cvrplib/Instance.py
cvrplib/__init__.py
cvrplib/constants.py
cvrplib/cvrp.py
cvrplib/download.py
cvrplib/instance_data.csv
cvrplib/list_names.py
cvrplib/parse_instance.py
cvrplib/parse_solution.py
cvrplib/read.py
cvrplib/utils.py
cvrplib/vrptw.py
cvrplib-0.1.2.dist-info/LICENSE
cvrplib-0.1.2.dist-info/WHEEL
cvrplib-0.1.2.dist-info/METADATA
cvrplib-0.1.2.dist-info/RECORD
