Metadata-Version: 2.1
Name: cvrplib
Version: 0.1.2
Summary: Python library for reading and downloading CVRPLIB instances.
Home-page: https://github.com/leonlan/CVRPLIB
License: MIT
Author: Leon Lan
Author-email: leon.lanyidong@gmail.com
Requires-Python: >=3.7,<4.0
Classifier: License :: OSI Approved :: MIT License
Classifier: Programming Language :: Python :: 3
Classifier: Programming Language :: Python :: 3.7
Classifier: Programming Language :: Python :: 3.8
Classifier: Programming Language :: Python :: 3.9
Classifier: Programming Language :: Python :: 3.10
Classifier: Programming Language :: Python :: 3.11
Requires-Dist: numpy (>=1.15,<2.0)
Requires-Dist: requests (>=2.27.1,<3.0.0)
Project-URL: Repository, https://github.com/leonlan/CVRPLIB
